quoteondemand/__init__.py
quoteondemand/__main__.py
quoteondemand/quotes.py
quote_ondemand-1.0.1.dist-info/LICENSE
quote_ondemand-1.0.1.dist-info/METADATA
quote_ondemand-1.0.1.dist-info/WHEEL
quote_ondemand-1.0.1.dist-info/entry_points.txt
quote_ondemand-1.0.1.dist-info/top_level.txt
quote_ondemand-1.0.1.dist-info/RECORD
