Metadata-Version: 2.1
Name: quote-ondemand
Version: 1.0.1
Summary: Get the quote from internet
Author-email: Anuj Sadani <anuj.k.sadani@gmail.com>
License: MIT License        
Project-URL: Homepage, https://github.com/anuj-sadani-infrrd/quote-ondemand
Keywords: quote,tutorial,random
Classifier: License :: OSI Approved :: MIT License
Classifier: Programming Language :: Python :: 3
Requires-Python: >=3.0
License-File: LICENSE
Requires-Dist: requests (>=2.22.0)
